gnucash_portfolio_webui/__init__.py
gnucash_portfolio_webui/__main__.py
gnucash_portfolio_webui/app.py
gnucash_portfolio_webui/config.py
gnucash_portfolio_webui/decorators.py
gnucash_portfolio_webui/run-vscode.py
gnucash_portfolio_webui/run.py
gnucash_portfolio_webui/controllers/__init__.py
gnucash_portfolio_webui/controllers/account_controller.py
gnucash_portfolio_webui/controllers/assetallocation_controller.py
gnucash_portfolio_webui/controllers/currency_controller.py
gnucash_portfolio_webui/controllers/distributions_controller.py
gnucash_portfolio_webui/controllers/index_controller.py
gnucash_portfolio_webui/controllers/portfolio_controller.py
gnucash_portfolio_webui/controllers/price_controller.py
gnucash_portfolio_webui/controllers/scheduled_controller.py
gnucash_portfolio_webui/controllers/securities_controller.py
gnucash_portfolio_webui/controllers/settings_controller.py
gnucash_portfolio_webui/controllers/transaction_controller.py
gnucash_portfolio_webui/controllers/vanguard.py
gnucash_portfolio_webui/infrastructure/__init__.py
gnucash_portfolio_webui/infrastructure/caching.py
gnucash_portfolio_webui/models/__init__.py
gnucash_portfolio_webui/models/account_models.py
gnucash_portfolio_webui/models/assetallocation_models.py
gnucash_portfolio_webui/models/currency_models.py
gnucash_portfolio_webui/models/distribution_models.py
gnucash_portfolio_webui/models/generic_models.py
gnucash_portfolio_webui/models/price_models.py
gnucash_portfolio_webui/models/security_models.py
gnucash_portfolio_webui/models/transaction_models.py
gnucash_portfolio_webui/node_modules/bootstrap/dist/js/bootstrap.min.js
gnucash_portfolio_webui/node_modules/chosen-js/chosen.jquery.min.js
gnucash_portfolio_webui/node_modules/chosen-js/chosen.min.css
gnucash_portfolio_webui/node_modules/datatables.net/js/jquery.dataTables.js
gnucash_portfolio_webui/node_modules/datatables.net-bs4/css/dataTables.bootstrap4.css
gnucash_portfolio_webui-1.3.6.dist-info/LICENSE
gnucash_portfolio_webui-1.3.6.dist-info/METADATA
gnucash_portfolio_webui-1.3.6.dist-info/WHEEL
gnucash_portfolio_webui-1.3.6.dist-info/entry_points.txt
gnucash_portfolio_webui-1.3.6.dist-info/top_level.txt
gnucash_portfolio_webui-1.3.6.dist-info/RECORD
