Metadata-Version: 2.1
Name: gnucash-portfolio-webui
Version: 1.3.6
Summary: Web UI for GnuCash Portfolio
Home-page: https://github.com/MisterY/gnucash-portfolio-webui
Author: Alen Siljak
Author-email: alen.siljak@gmx.com
License: UNKNOWN
Keywords: gnucash,finance,portfolio,webui
Platform: UNKNOWN
Classifier: Programming Language :: Python
Classifier: Programming Language :: Python :: 3
Classifier: Development Status :: 4 - Beta
Classifier: Environment :: Other Environment
Classifier: Intended Audience :: Developers
Classifier: License :: OSI Approved :: GNU Library or Lesser General Public License (LGPL)
Classifier: Operating System :: OS Independent
Classifier: Topic :: Software Development :: Libraries :: Python Modules
Requires-Dist: flask
Requires-Dist: flask-assets
Requires-Dist: gnucash-portfolio
